[
    {
        "name": "Россия",
        "position": "225p"
    },
    {
        "name": "Центр",
        "position": "225p3p"
    },
    {
        "name": "Москва и область",
        "position": "225p3p1p"
    },
    {
        "name": "Москва",
        "position": "225p3p1p213p"
    },
    {
        "name": "Балашиха",
        "position": "225p3p1p10716p"
    },
    {
        "name": "Воскресенск",
        "position": "225p3p1p10722p"
    },
    {
        "name": "Дмитров",
        "position": "225p3p1p10723p"
    },
    {
        "name": "Долгопрудный",
        "position": "225p3p1p214p"
    },
    {
        "name": "Дубна",
        "position": "225p3p1p215p"
    },
    {
        "name": "Железнодорожный",

        "position": "225p3p1p21622p"
    },
    {
        "name": "Жуковский",
        "position": "225p3p1p20571p"
    },
    {
        "name": "Ивантеевка",
        "position": "225p3p1p21623p"
    },
    {
        "name": "Климовск",
        "position": "225p3p1p37147p"
    },
    {
        "name": "Коломна",
        "position": "225p3p1p10734p"
    },
    {
        "name": "Королёв",
        "position": "225p3p1p20728p"
    },
    {
        "name": "Красногорск",
        "position": "225p3p1p10735p"
    },
    {
        "name": "Можайск",
        "position": "225p3p1p10739p"
    },
    {
        "name": "Орехово-Зуево",
        "position": "225p3p1p10745p"
    },
    {
        "name": "Подольск",
        "position": "225p3p1p10747p"
    },
    {
        "name": "Пущино",
        "position": "225p3p1p217p"
    },
    {
        "name": "Раменское",
        "position": "225p3p1p10750p"
    },
    {
        "name": "Сергиев Посад",
        "position": "225p3p1p10752p"
    },
    {
        "name": "Серпухов",
        "position": "225p3p1p10754p"
    },
    {
        "name": "Фрязино",
        "position": "225p3p1p21619p"
    },
    {
        "name": "Черноголовка",
        "position": "225p3p1p219p"
    },
    {
        "name": "Щелково",
        "position": "225p3p1p10765p"
    },
    {
        "name": "Юбилейный",
        "position": "225p3p1p21620p"
    },
    {
        "name": "Белгород и область",
        "position": "225p3p10645p"
    },
    {
        "name": "Белгород",
        "position": "225p3p10645p4p"
    },
    {
        "name": "Старый Оскол",
        "position": "225p3p10645p10649p"
    },
    {
        "name": "Брянск и область",
        "position": "225p3p10650p"
    },
    {
        "name": "Владимир и область",
        "position": "225p3p10658p"
    },
    {
        "name": "Владимир",
        "position": "225p3p10658p192p"
    },
    {
        "name": "Ковров",
        "position": "225p3p10658p10664p"
    },
    {
        "name": "Муром",
        "position": "225p3p10658p10668p"
    },
    {
        "name": "Воронеж и область",
        "position": "225p3p10672p"
    },
    {
        "name": "Иваново и область",
        "position": "225p3p10687p"
    },
    {
        "name": "Калуга и область",
        "position": "225p3p10693p"
    },
    {
        "name": "Калуга",
        "position": "225p3p10693p6p"
    },
    {
        "name": "Обнинск",
        "position": "225p3p10693p967p"
    },
    {
        "name": "Кострома и область",
        "position": "225p3p10699p"
    },
    {
        "name": "Курск и область",
        "position": "225p3p10705p"
    },
    {
        "name": "Железногорск",
        "position": "225p3p10705p10710p"
    },
    {
        "name": "Курск",
        "position": "225p3p10705p8p"
    },
    {
        "name": "Липецк и область",
        "position": "225p3p10712p"
    },
    {
        "name": "Орел и область",
        "position": "225p3p10772p"
    },
    {
        "name": "Рязань и область",
        "position": "225p3p10776p"
    },
    {
        "name": "Смоленск и область",
        "position": "225p3p10795p"
    },
    {
        "name": "Тамбов и область",
        "position": "225p3p10802p"
    },
    {
        "name": "Тверь и область",
        "position": "225p3p10819p"
    },
    {
        "name": "Тула и область",
        "position": "225p3p10832p"
    },
    {
        "name": "Новомосковск",
        "position": "225p3p10832p10830p"
    },
    {
        "name": "Тула",
        "position": "225p3p10832p15p"
    },
    {
        "name": "Ярославль и область",
        "position": "225p3p10841p"
    },
    {
        "name": "Рыбинск",
        "position": "225p3p10841p10839p"
    },
    {
        "name": "Тутаев",
        "position": "225p3p10841p21154p"
    },
    {
        "name": "Ярославль",
        "position": "225p3p10841p16p"
    },
    {
        "name": "Северо-Запад",
        "position": "225p17p"
    },
    {
        "name": "Санкт-Петербург и Ленинградская область",
        "position": "225p17p10174p"
    },
    {
        "name": "Волхов",
        "position": "225p17p10174p10864p"
    },
    {
        "name": "Всеволожск",
        "position": "225p17p10174p10865p"
    },
    {
        "name": "Выборг",
        "position": "225p17p10174p969p"
    },
    {
        "name": "Гатчина",
        "position": "225p17p10174p10867p"
    },
    {
        "name": "Кириши",
        "position": "225p17p10174p10871p"
    },
    {
        "name": "Санкт-Петербург",
        "position": "225p17p10174p2p"
    },
    {
        "name": "Сосновый Бор",
        "position": "225p17p10174p10891p"
    },
    {
        "name": "Тихвин",
        "position": "225p17p10174p10892p"
    },
    {
        "name": "Архангельск и область",
        "position": "225p17p10842p"
    },
    {
        "name": "Архангельск",
        "position": "225p17p10842p20p"
    },
    {
        "name": "Северодвинск",
        "position": "225p17p10842p10849p"
    },
    {
        "name": "Великий Новгород и Новгородская область",
        "position": "225p17p10904p"
    },
    {
        "name": "Вологда и область",
        "position": "225p17p10853p"
    },
    {
        "name": "Вологда",
        "position": "225p17p10853p21p"
    },
    {
        "name": "Череповец",
        "position": "225p17p10853p968p"
    },
    {
        "name": "Калининград и область",
        "position": "225p17p10857p"
    },
    {
        "name": "Мурманск и область",
        "position": "225p17p10897p"
    },
    {
        "name": "Апатиты",
        "position": "225p17p10897p10894p"
    },
    {
        "name": "Мурманск",
        "position": "225p17p10897p23p"
    },
    {
        "name": "Ненецкий автономный округ",
        "position": "225p17p10176p"
    },
    {
        "name": "Псков и область",
        "position": "225p17p10926p"
    },
    {
        "name": "Великие Луки",
        "position": "225p17p10926p10928p"
    },
    {
        "name": "Псков",
        "position": "225p17p10926p25p"
    },
    {
        "name": "Республика Карелия",
        "position": "225p17p10933p"
    },
    {
        "name": "Кондопога",
        "position": "225p17p10933p10934p"
    },
    {
        "name": "Петрозаводск",
        "position": "225p17p10933p18p"
    },
    {
        "name": "Сортавала",
        "position": "225p17p10933p10937p"
    },
    {
        "name": "Республика Коми",
        "position": "225p17p10939p"
    },
    {
        "name": "Воркута",
        "position": "225p17p10939p10940p"
    },
    {
        "name": "Сыктывкар",
        "position": "225p17p10939p19p"
    },
    {
        "name": "Усинск",
        "position": "225p17p10939p10944p"
    },
    {
        "name": "Ухта",
        "position": "225p17p10939p10945p"
    },
    {
        "name": "Поволжье",
        "position": "225p40p"
    },
    {
        "name": "Киров и область",
        "position": "225p40p11070p"
    },
    {
        "name": "Нижний Новгород и область",
        "position": "225p40p11079p"
    },
    {
        "name": "Выкса",
        "position": "225p40p11079p20040p"
    },
    {
        "name": "Дзержинск",
        "position": "225p40p11079p972p"
    },
    {
        "name": "Кстово",
        "position": "225p40p11079p20044p"
    },
    {
        "name": "Нижний Новгород",
        "position": "225p40p11079p47p"
    },
    {
        "name": "Саров",
        "position": "225p40p11079p11083p"
    },
    {
        "name": "Оренбург и область",
        "position": "225p40p11084p"
    },
    {
        "name": "Оренбург",
        "position": "225p40p11084p48p"
    },
    {
        "name": "Орск",
        "position": "225p40p11084p11091p"
    },
    {
        "name": "Пенза и область",
        "position": "225p40p11095p"
    },
    {
        "name": "Пермский край",
        "position": "225p40p11108p"
    },
    {
        "name": "Березники",
        "position": "225p40p11108p20237p"
    },
    {
        "name": "Пермь",
        "position": "225p40p11108p50p"
    },
    {
        "name": "Республика Башкортостан",
        "position": "225p40p11111p"
    },
    {
        "name": "Нефтекамск",
        "position": "225p40p11111p11114p"
    },
    {
        "name": "Октябрьский",
        "position": "225p40p11111p20235p"
    },
    {
        "name": "Салават",
        "position": "225p40p11111p11115p"
    },
    {
        "name": "Стерлитамак",
        "position": "225p40p11111p11116p"
    },
    {
        "name": "Уфа",
        "position": "225p40p11111p172p"
    },
    {
        "name": "Республика Марий Эл",
        "position": "225p40p11077p"
    },
    {
        "name": "Республика Мордовия",
        "position": "225p40p11117p"
    },
    {
        "name": "Республика Татарстан",
        "position": "225p40p11119p"
    },
    {
        "name": "Альметьевск",
        "position": "225p40p11119p11121p"
    },
    {
        "name": "Бугульма",
        "position": "225p40p11119p11122p"
    },
    {
        "name": "Казань",
        "position": "225p40p11119p43p"
    },
    {
        "name": "Набережные Челны",
        "position": "225p40p11119p236p"
    },
    {
        "name": "Нижнекамск",
        "position": "225p40p11119p11127p"
    },
    {
        "name": "Самара и область",
        "position": "225p40p11131p"
    },
    {
        "name": "Жигулевск",
        "position": "225p40p11131p11132p"
    },
    {
        "name": "Самара",
        "position": "225p40p11131p51p"
    },
    {
        "name": "Сызрань",
        "position": "225p40p11131p11139p"
    },
    {
        "name": "Тольятти",
        "position": "225p40p11131p240p"
    },
    {
        "name": "Саратов и область",
        "position": "225p40p11146p"
    },
    {
        "name": "Балаково",
        "position": "225p40p11146p11143p"
    },
    {
        "name": "Саратов",
        "position": "225p40p11146p194p"
    },
    {
        "name": "Энгельс",
        "position": "225p40p11146p11147p"
    },
    {
        "name": "Удмуртская Республика",
        "position": "225p40p11148p"
    },
    {
        "name": "Глазов",
        "position": "225p40p11148p11150p"
    },
    {
        "name": "Ижевск",
        "position": "225p40p11148p44p"
    },
    {
        "name": "Сарапул",
        "position": "225p40p11148p11152p"
    },
    {
        "name": "Ульяновск и область",
        "position": "225p40p11153p"
    },
    {
        "name": "Димитровград",
        "position": "225p40p11153p11155p"
    },
    {
        "name": "Ульяновск",
        "position": "225p40p11153p195p"
    },
    {
        "name": "Чувашская Республика",
        "position": "225p40p11156p"
    },
    {
        "name": "Новочебоксарск",
        "position": "225p40p11156p37133p"
    },
    {
        "name": "Чебоксары",
        "position": "225p40p11156p45p"
    },
    {
        "name": "Юг",
        "position": "225p26p"
    },
    {
        "name": "Астрахань и область",
        "position": "225p26p10946p"
    },
    {
        "name": "Волгоград и область",
        "position": "225p26p10950p"
    },
    {
        "name": "Волгоград",
        "position": "225p26p10950p38p"
    },
    {
        "name": "Волжский",
        "position": "225p26p10950p10951p"
    },
    {
        "name": "Камышин",
        "position": "225p26p10950p10959p"
    },
    {
        "name": "Краснодарский край",
        "position": "225p26p10995p"
    },
    {
        "name": "Анапа",
        "position": "225p26p10995p1107p"
    },
    {
        "name": "Армавир",
        "position": "225p26p10995p10987p"
    },
    {
        "name": "Ейск",
        "position": "225p26p10995p10993p"
    },
    {
        "name": "Краснодар",
        "position": "225p26p10995p35p"
    },
    {
        "name": "Новороссийск",
        "position": "225p26p10995p970p"
    },
    {
        "name": "Сочи",
        "position": "225p26p10995p239p"
    },
    {
        "name": "Туапсе",
        "position": "225p26p10995p1058p"
    },
    {
        "name": "Республика Адыгея",
        "position": "225p26p11004p"
    },
    {
        "name": "Республика Калмыкия",
        "position": "225p26p11015p"
    },
    {
        "name": "Ростов-на-Дону и область",
        "position": "225p26p11029p"
    },
    {
        "name": "Волгодонск",
        "position": "225p26p11029p11036p"
    },
    {
        "name": "Каменск-Шахтинский",
        "position": "225p26p11029p11043p"
    },
    {
        "name": "Новочеркасск",
        "position": "225p26p11029p238p"
    },
    {
        "name": "Ростов-на-Дону",
        "position": "225p26p11029p39p"
    },
    {
        "name": "Таганрог",
        "position": "225p26p11029p971p"
    },
    {
        "name": "Шахты",
        "position": "225p26p11029p11053p"
    },
    {
        "name": "Сибирь",
        "position": "225p59p"
    },
    {
        "name": "Алтайский край",
        "position": "225p59p11235p"
    },
    {
        "name": "Барнаул",
        "position": "225p59p11235p197p"
    },
    {
        "name": "Бийск",
        "position": "225p59p11235p975p"
    },
    {
        "name": "Забайкальский край",
        "position": "225p59p21949p"
    },
    {
        "name": "Иркутск и область",
        "position": "225p59p11266p"
    },
    {
        "name": "Ангарск",
        "position": "225p59p11266p11256p"
    },
    {
        "name": "Братск",
        "position": "225p59p11266p976p"
    },
    {
        "name": "Иркутск",
        "position": "225p59p11266p63p"
    },
    {
        "name": "Усть-Илимск",
        "position": "225p59p11266p11273p"
    },
    {
        "name": "Кемерово и область",
        "position": "225p59p11282p"
    },
    {
        "name": "Кемерово",
        "position": "225p59p11282p64p"
    },
    {
        "name": "Междуреченск",
        "position": "225p59p11282p11287p"
    },
    {
        "name": "Новокузнецк",
        "position": "225p59p11282p237p"
    },
    {
        "name": "Красноярский край",
        "position": "225p59p11309p"
    },
    {
        "name": "Ачинск",
        "position": "225p59p11309p11302p"
    },
    {
        "name": "Железногорск",
        "position": "225p59p11309p20086p"
    },
    {
        "name": "Красноярск",
        "position": "225p59p11309p62p"
    },
    {
        "name": "Минусинск",
        "position": "225p59p11309p11310p"
    },
    {
        "name": "Норильск",
        "position": "225p59p11309p11311p"
    },
    {
        "name": "Новосибирск и область",
        "position": "225p59p11316p"
    },
    {
        "name": "Омск и область",
        "position": "225p59p11318p"
    },
    {
        "name": "Республика Алтай",
        "position": "225p59p10231p"
    },
    {
        "name": "Республика Бурятия",
        "position": "225p59p11330p"
    },
    {
        "name": "Республика Тыва",
        "position": "225p59p10233p"
    },
    {
        "name": "Республика Хакасия",
        "position": "225p59p11340p"
    },
    {
        "name": "Томск и область",
        "position": "225p59p11353p"
    },
    {
        "name": "Северск",
        "position": "225p59p11353p11351p"
    },
    {
        "name": "Томск",
        "position": "225p59p11353p67p"
    },
    {
        "name": "Дальний Восток",
        "position": "225p73p"
    },
    {
        "name": "Благовещенск и Амурская область",
        "position": "225p73p11375p"
    },
    {
        "name": "Белогорск",
        "position": "225p73p11375p11374p"
    },
    {
        "name": "Благовещенск",
        "position": "225p73p11375p77p"
    },
    {
        "name": "Тында",
        "position": "225p73p11375p11391p"
    },
    {
        "name": "Еврейская автономная область",
        "position": "225p73p10243p"
    },
    {
        "name": "Камчатский край",
        "position": "225p73p11398p"
    },
    {
        "name": "Магадан и область",
        "position": "225p73p11403p"
    },
    {
        "name": "Приморский край",
        "position": "225p73p11409p"
    },
    {
        "name": "Владивосток",
        "position": "225p73p11409p75p"
    },
    {
        "name": "Находка",
        "position": "225p73p11409p974p"
    },
    {
        "name": "Уссурийск",
        "position": "225p73p11409p11426p"
    },
    {
        "name": "Республика Саха (Якутия)",
        "position": "225p73p11443p"
    },
    {
        "name": "Хабаровский край",
        "position": "225p73p11457p"
    },
    {
        "name": "Комсомольск-на-Амуре",
        "position": "225p73p11457p11453p"
    },
    {
        "name": "Хабаровск",
        "position": "225p73p11457p76p"
    },
    {
        "name": "Чукотский автономный округ",
        "position": "225p73p10251p"
    },
    {
        "name": "Южно-Сахалинск и Сахалинская область",
        "position": "225p73p11450p"
    },
    {
        "name": "Северный Кавказ",
        "position": "225p102444p"
    },
    {
        "name": "Кабардино-Балкарская Республика",
        "position": "225p102444p11013p"
    },
    {
        "name": "Карачаево-Черкесская Республика",
        "position": "225p102444p11020p"
    },
    {
        "name": "Республика Дагестан",
        "position": "225p102444p11010p"
    },
    {
        "name": "Республика Ингушетия",
        "position": "225p102444p11012p"
    },
    {
        "name": "Республика Северная Осетия-Алания",
        "position": "225p102444p11021p"
    },
    {
        "name": "Ставропольский край",
        "position": "225p102444p11069p"
    },
    {
        "name": "Ессентуки",
        "position": "225p102444p11069p11057p"
    },
    {
        "name": "Кисловодск",
        "position": "225p102444p11069p11062p"
    },
    {
        "name": "Минеральные Воды",
        "position": "225p102444p11069p11063p"
    },
    {
        "name": "Невинномысск",
        "position": "225p102444p11069p11064p"
    },
    {
        "name": "Пятигорск",
        "position": "225p102444p11069p11067p"
    },
    {
        "name": "Ставрополь",
        "position": "225p102444p11069p36p"
    },
    {
        "name": "Чеченская Республика",
        "position": "225p102444p11024p"
    },
    {
        "name": "Урал",
        "position": "225p52p"
    },
    {
        "name": "Екатеринбург и Свердловская область",
        "position": "225p52p11162p"
    },
    {
        "name": "Екатеринбург",
        "position": "225p52p11162p54p"
    },
    {
        "name": "Каменск-Уральский",
        "position": "225p52p11162p11164p"
    },
    {
        "name": "Нижний Тагил",
        "position": "225p52p11162p11168p"
    },
    {
        "name": "Первоуральск",
        "position": "225p52p11162p11171p"
    },
    {
        "name": "Курган и область",
        "position": "225p52p11158p"
    },
    {
        "name": "Тюмень и область",
        "position": "225p52p11176p"
    },
    {
        "name": "Ишим",
        "position": "225p52p11176p11173p"
    },
    {
        "name": "Тобольск",
        "position": "225p52p11176p11175p"
    },
    {
        "name": "Тюмень",
        "position": "225p52p11176p55p"
    },
    {
        "name": "Ханты-Мансийский автономный округ",
        "position": "225p52p11193p"
    },
    {
        "name": "Нефтеюганск",
        "position": "225p52p11193p11184p"
    },
    {
        "name": "Нижневартовск",
        "position": "225p52p11193p1091p"
    },
    {
        "name": "Сургут",
        "position": "225p52p11193p973p"
    },
    {
        "name": "Ханты-Мансийск",
        "position": "225p52p11193p57p"
    },
    {
        "name": "Челябинск и область",
        "position": "225p52p11225p"
    },
    {
        "name": "Магнитогорск",
        "position": "225p52p11225p235p"
    },
    {
        "name": "Миасс",
        "position": "225p52p11225p11212p"
    },
    {
        "name": "Озерск",
        "position": "225p52p11225p11214p"
    },
    {
        "name": "Сатка",
        "position": "225p52p11225p11217p"
    },
    {
        "name": "Челябинск",
        "position": "225p52p11225p56p"
    },
    {
        "name": "Ямало-Ненецкий автономный округ",
        "position": "225p52p11232p"
    },
    {
        "name": "Новый Уренгой",
        "position": "225p52p11232p11230p"
    },
    {
        "name": "Ноябрьск",
        "position": "225p52p11232p11231p"
    },
    {
        "name": "Салехард",
        "position": "225p52p11232p58p"
    },
    {
        "name": "СНГ (исключая Россию)",
        "position": "166p"
    },
    {
        "name": "Абхазия",
        "position": "166p29386p"
    },
    {
        "name": "Азербайджан",
        "position": "166p167p"
    },
    {
        "name": "Армения",
        "position": "166p168p"
    },
    {
        "name": "Беларусь",
        "position": "166p149p"
    },
    {
        "name": "Брест и область",
        "position": "166p149p29632p"
    },
    {
        "name": "Витебск и область",
        "position": "166p149p29633p"
    },
    {
        "name": "Гомель и область",
        "position": "166p149p29631p"
    },
    {
        "name": "Гродно и область",
        "position": "166p149p29634p"
    },
    {
        "name": "Минск и область",
        "position": "166p149p29630p"
    },
    {
        "name": "Могилёв и область",
        "position": "166p149p29629p"
    },
    {
        "name": "Казахстан",
        "position": "166p159p"
    },
    {
        "name": "Актау и Мангистауская область",
        "position": "166p159p29414p"
    },
    {
        "name": "Актобе и область",
        "position": "166p159p29404p"
    },
    {
        "name": "Астана и Акмолинская область",
        "position": "166p159p29403p"
    },
    {
        "name": "Астана",
        "position": "166p159p29403p163p"
    },
    {
        "name": "Кокшетау",
        "position": "166p159p29403p20809p"
    },
    {
        "name": "Атырау и область",
        "position": "166p159p29407p"
    },
    {
        "name": "Восточно-Казахстанская область",
        "position": "166p159p29408p"
    },
    {
        "name": "Семей",
        "position": "166p159p29408p165p"
    },
    {
        "name": "Усть-Каменогорск",
        "position": "166p159p29408p10306p"
    },
    {
        "name": "Западно-Казахстанская область",
        "position": "166p159p29410p"
    },
    {
        "name": "Караганда и область",
        "position": "166p159p29411p"
    },
    {
        "name": "Костанай и область",
        "position": "166p159p29412p"
    },
    {
        "name": "Кызылорда и область",
        "position": "166p159p29413p"
    },
    {
        "name": "Павлодар и область",
        "position": "166p159p29415p"
    },
    {
        "name": "Северо-Казахстанская область",
        "position": "166p159p29416p"
    },
    {
        "name": "Талдыкорган и Алматинская область",
        "position": "166p159p29406p"
    },
    {
        "name": "Алматы",
        "position": "166p159p29406p162p"
    },
    {
        "name": "Талдыкорган",
        "position": "166p159p29406p10303p"
    },
    {
        "name": "Тараз и Жамбылская область",
        "position": "166p159p29409p"
    },
    {
        "name": "Южно-Казахстанская область",
        "position": "166p159p29417p"
    },
    {
        "name": "Киргизия",
        "position": "166p207p"
    },
    {
        "name": "Молдова",
        "position": "166p208p"
    },
    {
        "name": "Таджикистан",
        "position": "166p209p"
    },
    {
        "name": "Туркмения",
        "position": "166p170p"
    },
    {
        "name": "Узбекистан",
        "position": "166p171p"
    },
    {
        "name": "Украина",
        "position": "166p187p"
    },
    {
        "name": "Восток",
        "position": "166p187p20525p"
    },
    {
        "name": "Днепропетровск и область",
        "position": "166p187p20525p20537p"
    },
    {
        "name": "Днепродзержинск",
        "position": "166p187p20525p20537p21775p"
    },
    {
        "name": "Днепропетровск",
        "position": "166p187p20525p20537p141p"
    },
    {
        "name": "Кривой Рог",
        "position": "166p187p20525p20537p10347p"
    },
    {
        "name": "Никополь",
        "position": "166p187p20525p20537p21773p"
    },
    {
        "name": "Павлоград",
        "position": "166p187p20525p20537p28401p"
    },
    {
        "name": "Донецк и область",
        "position": "166p187p20525p20536p"
    },
    {
        "name": "Горловка",
        "position": "166p187p20525p20536p21774p"
    },
    {
        "name": "Донецк",
        "position": "166p187p20525p20536p142p"
    },
    {
        "name": "Краматорск",
        "position": "166p187p20525p20536p20554p"
    },
    {
        "name": "Макеевка",
        "position": "166p187p20525p20536p24876p"
    },
    {
        "name": "Мариуполь",
        "position": "166p187p20525p20536p10366p"
    },
    {
        "name": "Запорожье и область",
        "position": "166p187p20525p20539p"
    },
    {
        "name": "Луганск и область",
        "position": "166p187p20525p20540p"
    },
    {
        "name": "Алчевск",
        "position": "166p187p20525p20540p24885p"
    },
    {
        "name": "Луганск",
        "position": "166p187p20525p20540p222p"
    },
    {
        "name": "Северодонецк",
        "position": "166p187p20525p20540p24893p"
    },
    {
        "name": "Харьков и область",
        "position": "166p187p20525p20538p"
    },
    {
        "name": "Запад",
        "position": "166p187p20524p"
    },
    {
        "name": "Ивано-Франковск и область",
        "position": "166p187p20524p20532p"
    },
    {
        "name": "Луцк и Волынская область",
        "position": "166p187p20524p20550p"
    },
    {
        "name": "Львов и область",
        "position": "166p187p20524p20529p"
    },
    {
        "name": "Ровно и область",
        "position": "166p187p20524p20534p"
    },
    {
        "name": "Тернополь и область",
        "position": "166p187p20524p20531p"
    },
    {
        "name": "Ужгород и Закарпатская область",
        "position": "166p187p20524p20530p"
    },
    {
        "name": "Хмельницкий и область",
        "position": "166p187p20524p20535p"
    },
    {
        "name": "Черновцы и область",
        "position": "166p187p20524p20533p"
    },
    {
        "name": "Крым",
        "position": "166p187p977p"
    },
    {
        "name": "Евпатория",
        "position": "166p187p977p11463p"
    },
    {
        "name": "Керчь",
        "position": "166p187p977p11464p"
    },
    {
        "name": "Севастополь",
        "position": "166p187p977p959p"
    },
    {
        "name": "Симферополь",
        "position": "166p187p977p146p"
    },
    {
        "name": "Феодосия",
        "position": "166p187p977p11469p"
    },
    {
        "name": "Ялта",
        "position": "166p187p977p11470p"
    },
    {
        "name": "Север",
        "position": "166p187p20528p"
    },
    {
        "name": "Сумы и область",
        "position": "166p187p20528p20552p"
    },
    {
        "name": "Чернигов и область",
        "position": "166p187p20528p20551p"
    },
    {
        "name": "Центр",
        "position": "166p187p20527p"
    },
    {
        "name": "Винница и область",
        "position": "166p187p20527p20545p"
    },
    {
        "name": "Житомир и область",
        "position": "166p187p20527p20547p"
    },
    {
        "name": "Киев и область",
        "position": "166p187p20527p20544p"
    },
    {
        "name": "Белая Церковь",
        "position": "166p187p20527p20544p10369p"
    },
    {
        "name": "Киев",
        "position": "166p187p20527p20544p143p"
    },
    {
        "name": "Кировоград и область",
        "position": "166p187p20527p20548p"
    },
    {
        "name": "Полтава и область",
        "position": "166p187p20527p20549p"
    },
    {
        "name": "Кременчуг",
        "position": "166p187p20527p20549p21609p"
    },
    {
        "name": "Полтава",
        "position": "166p187p20527p20549p964p"
    },
    {
        "name": "Черкассы и область",
        "position": "166p187p20527p20546p"
    },
    {
        "name": "Юг",
        "position": "166p187p20526p"
    },
    {
        "name": "Николаев и область",
        "position": "166p187p20526p20543p"
    },
    {
        "name": "Одесса и область",
        "position": "166p187p20526p20541p"
    },
    {
        "name": "Херсон и область",
        "position": "166p187p20526p20542p"
    },
    {
        "name": "Европа",
        "position": "111p"
    },
    {
        "name": "Австрия",
        "position": "111p113p"
    },
    {
        "name": "Бельгия",
        "position": "111p114p"
    },
    {
        "name": "Болгария",
        "position": "111p115p"
    },
    {
        "name": "Великобритания",
        "position": "111p102p"
    },
    {
        "name": "Венгрия",
        "position": "111p116p"
    },
    {
        "name": "Германия",
        "position": "111p96p"
    },
    {
        "name": "Греция",
        "position": "111p246p"
    },
    {
        "name": "Дания",
        "position": "111p203p"
    },
    {
        "name": "Испания",
        "position": "111p204p"
    },
    {
        "name": "Италия",
        "position": "111p205p"
    },
    {
        "name": "Кипр",
        "position": "111p20574p"
    },
    {
        "name": "Нидерланды",
        "position": "111p118p"
    },
    {
        "name": "Норвегия",
        "position": "111p119p"
    },
    {
        "name": "Польша",
        "position": "111p120p"
    },
    {
        "name": "Сербия",
        "position": "111p180p"
    },
    {
        "name": "Словакия",
        "position": "111p121p"
    },
    {
        "name": "Словения",
        "position": "111p122p"
    },
    {
        "name": "Страны Балтии",
        "position": "111p980p"
    },
    {
        "name": "Латвия",
        "position": "111p980p206p"
    },
    {
        "name": "Литва",
        "position": "111p980p117p"
    },
    {
        "name": "Эстония",
        "position": "111p980p179p"
    },
    {
        "name": "Турция",
        "position": "111p983p"
    },
    {
        "name": "Провинция Агры",
        "position": "111p983p103668p"
    },
    {
        "name": "Провинция Адана",
        "position": "111p983p103669p"
    },
    {
        "name": "Провинция Адыяман",
        "position": "111p983p103670p"
    },
    {
        "name": "Провинция Айдын",
        "position": "111p983p103671p"
    },
    {
        "name": "Провинция Аксарай",
        "position": "111p983p103672p"
    },
    {
        "name": "Провинция Амасья",
        "position": "111p983p103673p"
    },
    {
        "name": "Провинция Анкара",
        "position": "111p983p103674p"
    },
    {
        "name": "Провинция Анталья",
        "position": "111p983p103675p"
    },
    {
        "name": "Провинция Ардахан",
        "position": "111p983p103676p"
    },
    {
        "name": "Провинция Артвин",
        "position": "111p983p103677p"
    },
    {
        "name": "Провинция Афьонкарахисар",
        "position": "111p983p103678p"
    },
    {
        "name": "Провинция Байбурт",
        "position": "111p983p103679p"
    },
    {
        "name": "Провинция Балыкесир",
        "position": "111p983p103680p"
    },
    {
        "name": "Провинция Бартын",
        "position": "111p983p103681p"
    },
    {
        "name": "Провинция Батман",
        "position": "111p983p103682p"
    },
    {
        "name": "Провинция Биледжик",
        "position": "111p983p103683p"
    },
    {
        "name": "Провинция Бингёль",
        "position": "111p983p103684p"
    },
    {
        "name": "Провинция Битлис",
        "position": "111p983p103685p"
    },
    {
        "name": "Провинция Болу",
        "position": "111p983p103686p"
    },
    {
        "name": "Провинция Бурдур",
        "position": "111p983p103687p"
    },
    {
        "name": "Провинция Бурса",
        "position": "111p983p103688p"
    },
    {
        "name": "Провинция Ван",
        "position": "111p983p103689p"
    },
    {
        "name": "Провинция Газиантеп",
        "position": "111p983p103690p"
    },
    {
        "name": "Провинция Гиресун",
        "position": "111p983p103691p"
    },
    {
        "name": "Провинция Гюмюшхане",
        "position": "111p983p103692p"
    },
    {
        "name": "Провинция Денизли",
        "position": "111p983p103693p"
    },
    {
        "name": "Провинция Диярбакыр",
        "position": "111p983p103694p"
    },
    {
        "name": "Провинция Дюздже",
        "position": "111p983p103695p"
    },
    {
        "name": "Провинция Зонгулдак",
        "position": "111p983p103696p"
    },
    {
        "name": "Провинция Измир",
        "position": "111p983p103697p"
    },
    {
        "name": "Провинция Йозгат",
        "position": "111p983p103698p"
    },
    {
        "name": "Провинция Кайсери",
        "position": "111p983p103699p"
    },
    {
        "name": "Провинция Карабюк",
        "position": "111p983p103700p"
    },
    {
        "name": "Провинция Караман",
        "position": "111p983p103701p"
    },
    {
        "name": "Провинция Карс",
        "position": "111p983p103702p"
    },
    {
        "name": "Провинция Кастамону",
        "position": "111p983p103703p"
    },
    {
        "name": "Провинция Кахраманмараш",
        "position": "111p983p103704p"
    },
    {
        "name": "Провинция Килис",
        "position": "111p983p103705p"
    },
    {
        "name": "Провинция Коджаэли",
        "position": "111p983p103706p"
    },
    {
        "name": "Провинция Конья",
        "position": "111p983p103707p"
    },
    {
        "name": "Провинция Кыркларели",
        "position": "111p983p103708p"
    },
    {
        "name": "Провинция Кыршехир",
        "position": "111p983p103709p"
    },
    {
        "name": "Провинция Кырыккале",
        "position": "111p983p103710p"
    },
    {
        "name": "Провинция Кютахья",
        "position": "111p983p103711p"
    },
    {
        "name": "Провинция Малатья",
        "position": "111p983p103712p"
    },
    {
        "name": "Провинция Маниса",
        "position": "111p983p103713p"
    },
    {
        "name": "Провинция Мардин",
        "position": "111p983p103714p"
    },
    {
        "name": "Провинция Мерсин",
        "position": "111p983p103715p"
    },
    {
        "name": "Провинция Мугла",
        "position": "111p983p103716p"
    },
    {
        "name": "Провинция Муш",
        "position": "111p983p103717p"
    },
    {
        "name": "Провинция Невшехир",
        "position": "111p983p103718p"
    },
    {
        "name": "Провинция Нигде",
        "position": "111p983p103719p"
    },
    {
        "name": "Провинция Орду",
        "position": "111p983p103720p"
    },
    {
        "name": "Провинция Османие",
        "position": "111p983p103721p"
    },
    {
        "name": "Провинция Ризе",
        "position": "111p983p103722p"
    },
    {
        "name": "Провинция Сакарья",
        "position": "111p983p103723p"
    },
    {
        "name": "Провинция Самсун",
        "position": "111p983p103724p"
    },
    {
        "name": "Провинция Сивас",
        "position": "111p983p103725p"
    },
    {
        "name": "Провинция Сиирт",
        "position": "111p983p103726p"
    },
    {
        "name": "Провинция Синоп",
        "position": "111p983p103727p"
    },
    {
        "name": "Провинция Стамбул",
        "position": "111p983p103728p"
    },
    {
        "name": "Провинция Текирдаг",
        "position": "111p983p103729p"
    },
    {
        "name": "Провинция Токат",
        "position": "111p983p103730p"
    },
    {
        "name": "Провинция Трабзон",
        "position": "111p983p103731p"
    },
    {
        "name": "Провинция Тунджели",
        "position": "111p983p103732p"
    },
    {
        "name": "Провинция Ушак",
        "position": "111p983p103733p"
    },
    {
        "name": "Провинция Хаккяри",
        "position": "111p983p103734p"
    },
    {
        "name": "Провинция Хатай",
        "position": "111p983p103735p"
    },
    {
        "name": "Провинция Чанаккале",
        "position": "111p983p103736p"
    },
    {
        "name": "Провинция Чанкыры",
        "position": "111p983p103737p"
    },
    {
        "name": "Провинция Чорум",
        "position": "111p983p103738p"
    },
    {
        "name": "Провинция Шанлыурфа",
        "position": "111p983p103739p"
    },
    {
        "name": "Провинция Ширнак",
        "position": "111p983p103740p"
    },
    {
        "name": "Провинция Ыгдыр",
        "position": "111p983p103741p"
    },
    {
        "name": "Провинция Ыспарта",
        "position": "111p983p103742p"
    },
    {
        "name": "Провинция Эдирне",
        "position": "111p983p103743p"
    },
    {
        "name": "Провинция Элязыг",
        "position": "111p983p103744p"
    },
    {
        "name": "Провинция Эрзинджан",
        "position": "111p983p103745p"
    },
    {
        "name": "Провинция Эрзурум",
        "position": "111p983p103746p"
    },
    {
        "name": "Провинция Эскишехир",
        "position": "111p983p103747p"
    },
    {
        "name": "Провинция Ялова",
        "position": "111p983p103748p"
    },
    {
        "name": "Финляндия",
        "position": "111p123p"
    },
    {
        "name": "Франция",
        "position": "111p124p"
    },
    {
        "name": "Хорватия",
        "position": "111p10083p"
    },
    {
        "name": "Чехия",
        "position": "111p125p"
    },
    {
        "name": "Швейцария",
        "position": "111p126p"
    },
    {
        "name": "Швеция",
        "position": "111p127p"
    },
    {
        "name": "Азия",
        "position": "183p"
    },
    {
        "name": "Ближний Восток",
        "position": "183p1004p"
    },
    {
        "name": "Египет",
        "position": "183p1004p1056p"
    },
    {
        "name": "Израиль",
        "position": "183p1004p181p"
    },
    {
        "name": "Объединённые Арабские Эмираты",
        "position": "183p1004p210p"
    },
    {
        "name": "Грузия",
        "position": "183p169p"
    },
    {
        "name": "Индия",
        "position": "183p994p"
    },
    {
        "name": "Китай",
        "position": "183p134p"
    },
    {
        "name": "Таиланд",
        "position": "183p995p"
    },
    {
        "name": "Южная Корея",
        "position": "183p135p"
    },
    {
        "name": "Япония",
        "position": "183p137p"
    },
    {
        "name": "Африка",
        "position": "241p"
    },
    {
        "name": "Северная Америка",
        "position": "10002p"
    },
    {
        "name": "Канада",
        "position": "10002p95p"
    },
    {
        "name": "США",
        "position": "10002p84p"
    },
    {
        "name": "Южная Америка",
        "position": "10003p"
    },
    {
        "name": "Аргентина",
        "position": "10003p93p"
    },
    {
        "name": "Бразилия",
        "position": "10003p94p"
    },
    {
        "name": "Австралия и Океания",
        "position": "138p"
    },
    {
        "name": "Австралия",
        "position": "138p211p"
    },
    {
        "name": "Новая Зеландия",
        "position": "138p139p"
    }
]